CHANGES.rst
LICENCE
MANIFEST.in
README.rst
bootstrap.py
pavement.py
paver-minilib.zip
setup.cfg
setup.py
docs/Makefile
docs/make.bat
docs/source/changes.rst
docs/source/conf.py
docs/source/gh-pages.rst
docs/source/index.rst
docs/source/overview.rst
docs/source/sphinx.rst
docs/source/task.rst
docs/source/template.rst
src/github/__init__.py
src/github/tools/__init__.py
src/github/tools/gh_pages.py
src/github/tools/sphinx.py
src/github/tools/task.py
src/github/tools/template.py
src/github/tools/test/__init__.py
src/github/tools/test/test_gh_pages.py
src/github/tools/test/utils.py
src/github/tools/tmpl/gh/+gitignore+_tmpl
src/github/tools/tmpl/gh/LICENCE_tmpl
src/github/tools/tmpl/gh/MANIFEST.in
src/github/tools/tmpl/gh/README.rst
src/github/tools/tmpl/gh/bootstrap.py
src/github/tools/tmpl/gh/pavement.py_tmpl
src/github/tools/tmpl/gh/setup.cfg
src/github/tools/tmpl/gh/docs/source/conf.py_tmpl
src/github/tools/tmpl/gh/docs/source/index.rst_tmpl
src/github/tools/tmpl/gh/docs/source/_static/.gitignore
src/github/tools/tmpl/gh/docs/source/_templates/.gitignore
src/github/tools/tmpl/gh/src/+package+/__init__.py_tmpl
src/github/tools/tmpl/gh/support-files/readme.rst
src/github_tools.egg-info/PKG-INFO
src/github_tools.egg-info/SOURCES.txt
src/github_tools.egg-info/dependency_links.txt
src/github_tools.egg-info/entry_points.txt
src/github_tools.egg-info/namespace_packages.txt
src/github_tools.egg-info/not-zip-safe
src/github_tools.egg-info/requires.txt
src/github_tools.egg-info/top_level.txt
support-files/readme.rst