Metadata-Version: 1.0
Name: github-tools
Version: 0.1.7
Summary: Helpers for Python package hosting at GitHub
Home-page: http://dinoboff.github.com/github-tools/
Author: Damien Lebrun
Author-email: dinoboff@hotmail.com
License: BSD
Keywords: sphinx,github,paster
Platform: UNKNOWN
Classifier: Programming Language :: Python :: 2.5
Classifier: Development Status :: 4 - Beta
Classifier: Environment :: Console
Classifier: Intended Audience :: Developers
Classifier: License :: OSI Approved :: BSD License
Classifier: Operating System :: POSIX :: Linux
Classifier: Topic :: Documentation
Classifier: Topic :: Software Development :: Version Control
